<?xml version="1.0" encoding="utf-8" ?>
<dwsync>
<file name="captions.vtt" server="72.167.52.28/fitness/" local="132918372042512306" remote="132924583800000000" Dst="2" />
<file name="descriptions.vtt" server="72.167.52.28/fitness/" local="132917503932514239" remote="132917651400000000" Dst="2" />
<file name="ffc_audio.mp3" server="72.167.52.28/fitness/" local="132917503941679840" remote="132917651400000000" Dst="2" />
<file name="ffc_audio.ogg" server="72.167.52.28/fitness/" local="132917503948300900" remote="132917651400000000" Dst="2" />
<file name="ffc_video.mp4" server="72.167.52.28/fitness/" local="132917503955243823" remote="132917651400000000" Dst="2" />
<file name="ffc_video.webm" server="72.167.52.28/fitness/" local="132917503915827306" remote="132917651400000000" Dst="2" />
<file name="burpees-descriptions.vtt" server="72.167.52.28/fitness/" local="132920098781698202" remote="132924583800000000" Dst="2" />
<file name="burpees.mp4" server="72.167.52.28/fitness/" local="132920098780613701" remote="132924583800000000" Dst="2" />
<file name="mountain-descriptions.vtt" server="72.167.52.28/fitness/" local="132920098933767066" remote="132924583800000000" Dst="2" />
<file name="mc.mp4" server="72.167.52.28/fitness/" local="132920098783126039" remote="132924583800000000" Dst="2" />
<file name="plank-descriptions.vtt" server="72.167.52.28/fitness/" local="132920098778791826" remote="132924583800000000" Dst="2" />
<file name="plank.mp4" server="72.167.52.28/fitness/" local="132920098935200840" remote="132924583800000000" Dst="2" />
</dwsync>